{
  "reportDate": "2026-06-18T04:38:00Z",
  "verdict": "NOT READY",
  "readinessScore": 35,
  "targetScore": 85,
  "apiEvidence": {
    "baseUrl": "http://15.207.65.184:5000",
    "probes": [
      {
        "endpoint": "GET /api/health",
        "status": 200,
        "body": {
          "status": "ok",
          "ready": true,
          "ts": "2026-06-18T04:35:36.253Z",
          "uptimeSeconds": 344262
        },
        "pass": true
      },
      {
        "endpoint": "GET /api/app/customer/ride/pending-recovery",
        "status": 404,
        "body": {
          "message": "API endpoint not found"
        },
        "pass": false,
        "expected": 401,
        "note": "H1 backend not deployed on EC2"
      },
      {
        "endpoint": "GET /api/ops/seed-test-accounts",
        "status": 410,
        "body": {
          "message": "Test account seeding is disabled for this environment",
          "appEnv": "production"
        },
        "pass": true,
        "note": "Correct production safety behavior"
      }
    ]
  },
  "neonEvidence": {
    "projectId": "floral-thunder-84852945",
    "projectName": "jago-production",
    "accessAttempt": "neonctl OAuth + API refresh",
    "result": "BLOCKED",
    "error": "Token refresh failed (400); browser auth pending",
    "priorSchemaAudit": {
      "booking_intents": false,
      "customer_payments_booking_intent_id": false,
      "payment_recovery_events": false,
      "migration0010": false,
      "migration0019": false,
      "migration0018": true
    }
  },
  "ec2Evidence": {
    "host": "15.207.65.184",
    "sshKeyTried": "C:\\Users\\kiran\\Downloads\\jago-server-key.pem",
    "usersTried": ["ubuntu", "ec2-user", "admin", "root", "bitnami"],
    "result": "BLOCKED",
    "error": "Permission denied (publickey) for all users"
  },
  "stagingEvidence": {
    "stagingUrl": "https://staging.jagopro.org",
    "result": "UNREACHABLE",
    "note": "Connection/SSL failure from validation network"
  },
  "e2eMatrix": {
    "login": "NOT_RUN",
    "rideBooking": "NOT_RUN",
    "driverAccept": "NOT_RUN",
    "tripComplete": "NOT_RUN",
    "parcelBooking": "NOT_RUN",
    "parcelDelivery": "NOT_RUN",
    "onlinePayment": "NOT_RUN",
    "paymentRecovery": "NOT_RUN",
    "blocker": "Infrastructure access + H1 deploy + QA seed"
  },
  "blockers": [
    "Neon production OAuth expired — complete: npx neonctl auth",
    "EC2 SSH key jago-server-key.pem not authorized on 15.207.65.184",
    "H1 pending-recovery returns 404 — backend not deployed",
    "Migrations 0010 and 0019 not applied on Neon production",
    "Staging environment unreachable for QA seeding"
  ],
  "unblockCommands": {
    "neonVerify": "node scripts/neon-production-ops.cjs verify",
    "neonApply": "node scripts/neon-production-ops.cjs apply",
    "ec2Deploy": "cd /var/www/jago && git pull origin master && npm ci && npm run build && pm2 startOrReload ecosystem.config.cjs --env production",
    "postDeployVerify": "curl -s -o /dev/null -w '%{http_code}' http://127.0.0.1:5000/api/app/customer/ride/pending-recovery"
  }
}
